np_validator/__init__.py
np_validator/comparators.py
np_validator/core.py
np_validator/exceptions.py
np_validator/models/__init__.py
np_validator/models/schemas.py
np_validator/models/utils.py
np_validator/path_matching.py
np_validator/processors.py
np_validator/sync_dataset.py
np_validator/validators.py
np_validator-0.10.0.dist-info/LICENSE
np_validator-0.10.0.dist-info/WHEEL
np_validator-0.10.0.dist-info/METADATA
np_validator-0.10.0.dist-info/RECORD
