Metadata-Version: 2.1
Name: np-validator
Version: 0.10.0
Summary: Awesome `np-validator` is a Python cli/package created with https://github.com/TezRomacH/python-package-template
Home-page: https://github.com/np_validator/np-validator
License: MIT
Author: np-validator
Author-email: chrism@alleninstitute.org
Requires-Python: >=3.9,<4.0
Classifier: Development Status :: 3 - Alpha
Classifier: Intended Audience :: Developers
Classifier: License :: OSI Approved :: MIT License
Classifier: Operating System :: OS Independent
Classifier: Programming Language :: Python :: 3
Classifier: Programming Language :: Python :: 3.10
Classifier: Programming Language :: Python :: 3.7
Classifier: Programming Language :: Python :: 3.8
Classifier: Programming Language :: Python :: 3.9
Classifier: Topic :: Software Development :: Libraries :: Python Modules
Requires-Dist: PyYAML (>=6.0,<7.0)
Requires-Dist: h5py (>=3.7.0,<4.0.0)
Requires-Dist: importlib_metadata (>=4.5.0,<5.0.0); python_version < "3.8"
Requires-Dist: marshmallow (>=3.17.0,<4.0.0)
Requires-Dist: np-lims-tk (>=0.9.1,<0.10.0)
Requires-Dist: numpy (>=1.22.3,<2.0.0); python_version >= "3.8" and python_version < "4.0"
Requires-Dist: rich (>=12.5.1,<13.0.0)
Requires-Dist: typer (>=0.6.1,<0.7.0)
Project-URL: Repository, https://github.com/np_validator/np-validator
